setup.py
flask_hooks/__init__.py
flask_hooks.egg-info/PKG-INFO
flask_hooks.egg-info/SOURCES.txt
flask_hooks.egg-info/dependency_links.txt
flask_hooks.egg-info/requires.txt
flask_hooks.egg-info/top_level.txt