Metadata-Version: 1.0
Name: flask-hooks
Version: 0.0.2
Summary: flask hook tools
Home-page: UNKNOWN
Author: UNKNOWN
Author-email: UNKNOWN
License: UNKNOWN
Platform: UNKNOWN
